{"name":"Giant Shark","size":"huge","type":"beast","subtype":"","alignment":"unaligned","armor_class":13,"hit_points":"11","speed":"swim 50 ft.","ability_scores":{"strength":23,"dexterity":11,"constitution":21,"intelligence":1,"wisdom":10,"charisma":5},"saving_throws":{"strength":null,"dexterity":null,"constitution":null,"intelligence":null,"wisdom":null,"charisma":null},"skills":{"athletics":null,"acrobatics":null,"sleight_of_hand":null,"stealth":null,"demolitions":null,"history":null,"investigation":null,"nature":null,"religion":null,"repair":null,"security":null,"arcana":null,"animal_handling":null,"insight":null,"medicine":null,"perception":3,"survival":null,"deception":null,"intimidation":null,"performance":null,"persuasion":null},"damage_vulnerabilities":"","damage_resistances":"","damage_immunities":"","condition_immunities":"","senses":"blindsight 60 ft., passive Perception 13","languages":"","challenge":"5","special_abilities":[{"name":"Blood Frenzy","desc":"The shark has advantage on melee attack rolls against any creature that doesn't have all its hit points.","attack_bonus":0},{"name":"Water Breathing","desc":"The shark can breathe only underwater.","attack_bonus":0}],"actions":[{"name":"Bite","desc":"Weapon Attack: +9 to hit, reach 5 ft., one target. Hit: 22 (3d10 + 6) piercing damage.","attack_bonus":9,"damage_dice":"3d10","damage_bonus":6}]}